settle_poker/__init__.py
settle_poker/session.py
settle_poker/solver.py
settle_poker-0.1.0.dist-info/LICENSE
settle_poker-0.1.0.dist-info/METADATA
settle_poker-0.1.0.dist-info/WHEEL
settle_poker-0.1.0.dist-info/RECORD
