Metadata-Version: 2.1
Name: settle-poker
Version: 0.1.0
Summary: Package to handle poker settlements
License: MIT
Author: Jayanth Yindukuri
Author-email: 58279279+j-tesla@users.noreply.github.com 
Requires-Python: >=3.10,<4.0
Classifier: License :: OSI Approved :: MIT License
Classifier: Programming Language :: Python :: 3
Classifier: Programming Language :: Python :: 3.10
Classifier: Programming Language :: Python :: 3.11
Classifier: Programming Language :: Python :: 3.12
Requires-Dist: ortools (>=9.10.4067,<10.0.0)
